{
  "format_version": "1.10.0",
  "minecraft:client_entity": {
    "description": {
      "animations": {
        "default": "animation.auctioneer.idle"
      },
      "geometry": {
        "default": "geometry.auctioneer"
      },
      "identifier": "npc:auctioneer",
      "materials": {
        "default": "npc"
      },
      "render_controllers": [
        "controller.render.default"
      ],
      "scripts": {
        "animate": [
          "default"
        ]
      },
      "textures": {
        "default": "textures/entity/npc/auctioneer"
      }
    }
  }
}
